fpgrowth_py/__init__.py
fpgrowth_py/fpgrowth.py
fpgrowth_py/utils.py
fpgrowth_py-1.0.0.dist-info/LICENSE.txt
fpgrowth_py-1.0.0.dist-info/METADATA
fpgrowth_py-1.0.0.dist-info/WHEEL
fpgrowth_py-1.0.0.dist-info/top_level.txt
fpgrowth_py-1.0.0.dist-info/RECORD
