Metadata-Version: 2.1
Name: fpgrowth_py
Version: 1.0.0
Summary: Python implementation of FP Growth algorithm
Home-page: https://github.com/chonyy/fpgrowth_py
Author: Chonyy
Author-email: tcheon8788@gmail.com
License: UNKNOWN
Platform: UNKNOWN
Classifier: Programming Language :: Python :: 3
Classifier: License :: OSI Approved :: MIT License
Classifier: Operating System :: OS Independent
Requires-Python: >=3.6
